{"page":{"body":{"content":{"style":{"color":"#000000","font-family":"Arial, 'Helvetica Neue', Helvetica, sans-serif"},"computedStyle":{"messageBackgroundColor":"transparent","linkColor":"#0068A5","messageWidth":"650px"}},"container":{"style":{"background-color":"#FFFFFF"}},"type":"mailup-bee-page-properties","webFonts":[{"name":"Montserrat","fontFamily":"'Montserrat', 'Trebuchet MS', 'Lucida Grande', 'Lucida Sans Unicode', 'Lucida Sans', Tahoma, sans-serif","url":"https://fonts.googleapis.com/css?family=Montserrat"},{"name":"Roboto","fontFamily":"'Roboto', Tahoma, Verdana, Segoe, sans-serif","url":"https://fonts.googleapis.com/css?family=Roboto"}]},"rows":[{"content":{"style":{"background-image":"none","background-repeat":"no-repeat","color":"#000000","width":"650px","background-position":"top left","background-color":"#4C414A"},"computedStyle":{"rowColStackOnMobile":true}},"container":{"style":{"background-image":"none","background-position":"top left","background-repeat":"no-repeat","background-color":"#E2DFD7"}},"locked":false,"columns":[{"grid-columns":12,"modules":[{"descriptor":{"image":{"src":"https://d15k2d11r6t6rl.cloudfront.net/public/users/Integrators/19b7eae6-38f6-4531-a9f9-0c76e74fab9f/leadsengage_int379/logoLVP.png","alt":"Image","href":""},"style":{"width":"100%","padding-top":"25px","padding-right":"25px","padding-bottom":"25px","padding-left":"25px"},"computedStyle":{"width":150,"class":"center  autowidth ","hideContentOnMobile":false}},"type":"mailup-bee-newsletter-modules-image","locked":false}],"style":{"padding-bottom":"0px","border-left":"0px dotted transparent","border-bottom":"0px dotted transparent","border-top":"0px dotted transparent","padding-right":"0px","border-right":"0px dotted transparent","padding-top":"0px","background-color":"transparent","padding-left":"0px"}}],"type":"one-column-empty"},{"content":{"style":{"background-image":"none","background-repeat":"no-repeat","color":"#333","width":"650px","background-position":"top left","background-color":"#4C414A"},"computedStyle":{"rowColStackOnMobile":true}},"container":{"style":{"background-image":"none","background-position":"top left","background-repeat":"no-repeat","background-color":"#E2DFD7"}},"locked":false,"columns":[{"grid-columns":3,"modules":[{"descriptor":{"text":{"style":{"color":"#FFFFFF","font-family":"inherit","line-height":"120%"},"html":"<div class=\"txtTinyMce-wrapper\" style=\"font-size: 12px; line-height: 14px;\" data-mce-style=\"font-size: 12px; line-height: 14px;\">\n<p style=\"font-size: 14px; line-height: 16px; text-align: center;\" data-mce-style=\"font-size: 14px; line-height: 16px; text-align: center;\"><span style=\"font-size: 12px; line-height: 14px;\" data-mce-style=\"font-size: 12px; line-height: 14px;\">ATTRACTIONS</span></p>\n</div>","computedStyle":{"linkColor":"#0068A5"}},"style":{"padding-top":"10px","padding-right":"10px","padding-left":"10px","padding-bottom":"10px"},"computedStyle":{"hideContentOnMobile":false}},"type":"mailup-bee-newsletter-modules-text","locked":false}],"style":{"padding-bottom":"5px","border-left":"0px solid transparent","border-bottom":"0px solid transparent","border-top":"0px solid transparent","padding-right":"0px","border-right":"0px solid transparent","padding-top":"5px","background-color":"transparent","padding-left":"0px"}},{"grid-columns":3,"modules":[{"descriptor":{"text":{"style":{"color":"#FFFFFF","font-family":"inherit","line-height":"120%"},"html":"<div class=\"txtTinyMce-wrapper\" style=\"font-size: 12px; line-height: 14px;\" data-mce-style=\"font-size: 12px; line-height: 14px;\">\n<p style=\"font-size: 14px; line-height: 16px; text-align: center;\" data-mce-style=\"font-size: 14px; line-height: 16px; text-align: center;\"><span style=\"font-size: 12px; line-height: 14px;\" data-mce-style=\"font-size: 12px; line-height: 14px;\">EVENTS</span></p>\n</div>","computedStyle":{"linkColor":"#0068A5"}},"style":{"padding-top":"10px","padding-right":"10px","padding-left":"10px","padding-bottom":"10px"},"computedStyle":{"hideContentOnMobile":false}},"type":"mailup-bee-newsletter-modules-text","locked":false}],"style":{"padding-bottom":"5px","border-left":"0px solid transparent","border-bottom":"0px solid transparent","border-top":"0px solid transparent","padding-right":"0px","border-right":"0px solid transparent","padding-top":"5px","background-color":"transparent","padding-left":"0px"}},{"grid-columns":3,"modules":[{"descriptor":{"text":{"style":{"color":"#FFFFFF","font-family":"inherit","line-height":"120%"},"html":"<div class=\"txtTinyMce-wrapper\" style=\"font-size: 12px; line-height: 14px;\" data-mce-style=\"font-size: 12px; line-height: 14px;\">\n<p style=\"font-size: 14px; line-height: 16px; text-align: center;\" data-mce-style=\"font-size: 14px; line-height: 16px; text-align: center;\"><span style=\"font-size: 12px; line-height: 14px;\" data-mce-style=\"font-size: 12px; line-height: 14px;\">SERVICES</span></p>\n</div>","computedStyle":{"linkColor":"#0068A5"}},"style":{"padding-top":"10px","padding-right":"10px","padding-left":"10px","padding-bottom":"10px"},"computedStyle":{"hideContentOnMobile":false}},"type":"mailup-bee-newsletter-modules-text","locked":false}],"style":{"padding-bottom":"5px","border-left":"0px solid transparent","border-bottom":"0px solid transparent","border-top":"0px solid transparent","padding-right":"0px","border-right":"0px solid transparent","padding-top":"5px","background-color":"transparent","padding-left":"0px"}},{"grid-columns":3,"modules":[{"descriptor":{"text":{"style":{"color":"#FFFFFF","font-family":"inherit","line-height":"120%"},"html":"<div class=\"txtTinyMce-wrapper\" style=\"font-size: 12px; line-height: 14px;\" data-mce-style=\"font-size: 12px; line-height: 14px;\">\n<p style=\"font-size: 14px; line-height: 16px; text-align: center;\" data-mce-style=\"font-size: 14px; line-height: 16px; text-align: center;\"><span style=\"font-size: 12px; line-height: 14px;\" data-mce-style=\"font-size: 12px; line-height: 14px;\">CONTACTS</span></p>\n</div>","computedStyle":{"linkColor":"#0068A5"}},"style":{"padding-top":"10px","padding-right":"10px","padding-left":"10px","padding-bottom":"10px"},"computedStyle":{"hideContentOnMobile":false}},"type":"mailup-bee-newsletter-modules-text","locked":false}],"style":{"padding-bottom":"5px","border-left":"0px solid transparent","border-bottom":"0px solid transparent","border-top":"0px solid transparent","padding-right":"0px","border-right":"0px solid transparent","padding-top":"5px","background-color":"transparent","padding-left":"0px"}}],"type":"four-columns-empty"},{"content":{"style":{"background-image":"none","background-repeat":"no-repeat","color":"#000000","width":"650px","background-position":"top left","background-color":"transparent"},"computedStyle":{"rowColStackOnMobile":true}},"container":{"style":{"background-image":"url('https://d15k2d11r6t6rl.cloudfront.net/public/users/Integrators/19b7eae6-38f6-4531-a9f9-0c76e74fab9f/leadsengage_int379/mainbgl.png')","background-position":"top center","background-repeat":"no-repeat","background-color":"#E2DFD7"}},"locked":false,"columns":[{"grid-columns":12,"modules":[{"descriptor":{"text":{"style":{"color":"#555555","font-family":"inherit","line-height":"120%"},"html":"<div class=\"txtTinyMce-wrapper\" data-mce-style=\"font-size: 12px; line-height: 14px;\" style=\"font-size: 12px; line-height: 14px;\"><p data-mce-style=\"font-size: 12px; line-height: 14px;\" style=\"font-size: 12px; line-height: 14px;\"><br data-mce-bogus=\"1\"></p></div>","computedStyle":{"linkColor":"#0068A5"}},"style":{"padding-top":"15px","padding-right":"15px","padding-left":"15px","padding-bottom":"15px"},"computedStyle":{"hideContentOnMobile":false}},"type":"mailup-bee-newsletter-modules-text","locked":false},{"descriptor":{"text":{"style":{"color":"#FFFFFF","font-family":"'Montserrat', 'Trebuchet MS', 'Lucida Grande', 'Lucida Sans Unicode', 'Lucida Sans', Tahoma, sans-serif","line-height":"120%"},"html":"<div class=\"txtTinyMce-wrapper\" style=\"font-size: 12px; line-height: 14px; font-family: Montserrat, 'Trebuchet MS', 'Lucida Grande', 'Lucida Sans Unicode', 'Lucida Sans', Tahoma, sans-serif;\" data-mce-style=\"font-size: 12px; line-height: 14px; font-family: Montserrat, 'Trebuchet MS', 'Lucida Grande', 'Lucida Sans Unicode', 'Lucida Sans', Tahoma, sans-serif;\">\n<p style=\"font-size: 14px; line-height: 16px; text-align: center;\" data-mce-style=\"font-size: 14px; line-height: 16px; text-align: center;\"><span style=\"font-size: 34px; line-height: 40px;\" data-mce-style=\"font-size: 34px; line-height: 40px;\"><strong><span style=\"line-height: 40px; font-size: 34px;\" data-mce-style=\"line-height: 40px; font-size: 34px;\">Welcome to Las Vegas</span></strong></span></p>\n</div>","computedStyle":{"linkColor":"#0068A5"}},"style":{"padding-top":"10px","padding-right":"10px","padding-left":"10px","padding-bottom":"10px"},"computedStyle":{"hideContentOnMobile":false}},"type":"mailup-bee-newsletter-modules-text","locked":false},{"descriptor":{"text":{"style":{"color":"#FFFFFF","font-family":"'Montserrat', 'Trebuchet MS', 'Lucida Grande', 'Lucida Sans Unicode', 'Lucida Sans', Tahoma, sans-serif","line-height":"120%"},"html":"<div class=\"txtTinyMce-wrapper\" style=\"font-size: 12px; line-height: 14px; font-family: Montserrat, 'Trebuchet MS', 'Lucida Grande', 'Lucida Sans Unicode', 'Lucida Sans', Tahoma, sans-serif;\" data-mce-style=\"font-size: 12px; line-height: 14px; font-family: Montserrat, 'Trebuchet MS', 'Lucida Grande', 'Lucida Sans Unicode', 'Lucida Sans', Tahoma, sans-serif;\">\n<p style=\"font-size: 14px; line-height: 16px; text-align: center;\" data-mce-style=\"font-size: 14px; line-height: 16px; text-align: center;\"><span style=\"font-size: 22px; line-height: 26px;\" data-mce-style=\"font-size: 22px; line-height: 26px;\">Best events and attractions</span></p>\n</div>","computedStyle":{"linkColor":"#0068A5"}},"style":{"padding-top":"10px","padding-right":"10px","padding-left":"10px","padding-bottom":"10px"},"computedStyle":{"hideContentOnMobile":false}},"type":"mailup-bee-newsletter-modules-text","locked":false},{"descriptor":{"text":{"style":{"color":"#555555","font-family":"inherit","line-height":"120%"},"html":"<div class=\"txtTinyMce-wrapper\" data-mce-style=\"font-size: 12px; line-height: 14px;\" style=\"font-size: 12px; line-height: 14px;\"><p data-mce-style=\"font-size: 12px; line-height: 14px;\" style=\"font-size: 12px; line-height: 14px;\"><br data-mce-bogus=\"1\"></p></div>","computedStyle":{"linkColor":"#0068A5"}},"style":{"padding-top":"20px","padding-right":"20px","padding-left":"20px","padding-bottom":"20px"},"computedStyle":{"hideContentOnMobile":false}},"type":"mailup-bee-newsletter-modules-text","locked":false},{"descriptor":{"text":{"style":{"color":"#555555","font-family":"inherit","line-height":"120%"},"html":"<div class=\"txtTinyMce-wrapper\" data-mce-style=\"font-size: 12px; line-height: 14px;\" style=\"font-size: 12px; line-height: 14px;\"><p data-mce-style=\"font-size: 12px; line-height: 14px;\" style=\"font-size: 12px; line-height: 14px;\"><br data-mce-bogus=\"1\"></p></div>","computedStyle":{"linkColor":"#0068A5"}},"style":{"padding-top":"30px","padding-right":"30px","padding-left":"30px","padding-bottom":"30px"},"computedStyle":{"hideContentOnMobile":false}},"type":"mailup-bee-newsletter-modules-text","locked":false},{"descriptor":{"text":{"style":{"color":"#555555","font-family":"inherit","line-height":"120%"},"html":"<div class=\"txtTinyMce-wrapper\" data-mce-style=\"font-size: 12px; line-height: 14px;\" style=\"font-size: 12px; line-height: 14px;\"><p data-mce-style=\"font-size: 12px; line-height: 14px;\" style=\"font-size: 12px; line-height: 14px;\"><br data-mce-bogus=\"1\"></p></div>","computedStyle":{"linkColor":"#0068A5"}},"style":{"padding-top":"30px","padding-right":"30px","padding-left":"30px","padding-bottom":"30px"},"computedStyle":{"hideContentOnMobile":false}},"type":"mailup-bee-newsletter-modules-text","locked":false},{"descriptor":{"text":{"style":{"color":"#555555","font-family":"inherit","line-height":"120%"},"html":"<div class=\"txtTinyMce-wrapper\" data-mce-style=\"font-size: 12px; line-height: 14px;\" style=\"font-size: 12px; line-height: 14px;\"><p data-mce-style=\"font-size: 12px; line-height: 14px;\" style=\"font-size: 12px; line-height: 14px;\"><br data-mce-bogus=\"1\"></p></div>","computedStyle":{"linkColor":"#0068A5"}},"style":{"padding-top":"30px","padding-right":"30px","padding-left":"30px","padding-bottom":"30px"},"computedStyle":{"hideContentOnMobile":false}},"type":"mailup-bee-newsletter-modules-text","locked":false},{"descriptor":{"text":{"style":{"color":"#555555","font-family":"inherit","line-height":"120%"},"html":"<div class=\"txtTinyMce-wrapper\" data-mce-style=\"font-size: 12px; line-height: 14px;\" style=\"font-size: 12px; line-height: 14px;\"><p data-mce-style=\"font-size: 12px; line-height: 14px;\" style=\"font-size: 12px; line-height: 14px;\"><br data-mce-bogus=\"1\"></p></div>","computedStyle":{"linkColor":"#0068A5"}},"style":{"padding-top":"30px","padding-right":"30px","padding-left":"30px","padding-bottom":"30px"},"computedStyle":{"hideContentOnMobile":false}},"type":"mailup-bee-newsletter-modules-text","locked":false},{"descriptor":{"text":{"style":{"color":"#555555","font-family":"inherit","line-height":"120%"},"html":"<div class=\"txtTinyMce-wrapper\" data-mce-style=\"font-size: 12px; line-height: 14px;\" style=\"font-size: 12px; line-height: 14px;\"><p data-mce-style=\"font-size: 12px; line-height: 14px;\" style=\"font-size: 12px; line-height: 14px;\"><br data-mce-bogus=\"1\"></p></div>","computedStyle":{"linkColor":"#0068A5"}},"style":{"padding-top":"30px","padding-right":"30px","padding-left":"30px","padding-bottom":"30px"},"computedStyle":{"hideContentOnMobile":false}},"type":"mailup-bee-newsletter-modules-text","locked":false},{"descriptor":{"text":{"style":{"color":"#555555","font-family":"inherit","line-height":"120%"},"html":"<div class=\"txtTinyMce-wrapper\" style=\"font-size: 12px; line-height: 14px;\" data-mce-style=\"font-size: 12px; line-height: 14px;\">\n<p style=\"font-size: 12px; line-height: 14px;\" data-mce-style=\"font-size: 12px; line-height: 14px;\">&nbsp;</p>\n</div>","computedStyle":{"linkColor":"#0068A5"}},"style":{"padding-top":"0px","padding-right":"0px","padding-left":"0px","padding-bottom":"0px"},"computedStyle":{"hideContentOnMobile":false}},"type":"mailup-bee-newsletter-modules-text","locked":false}],"style":{"padding-bottom":"0px","border-left":"0px solid transparent","border-bottom":"0px solid transparent","border-top":"0px solid transparent","padding-right":"0px","border-right":"0px solid transparent","padding-top":"0px","background-color":"transparent","padding-left":"0px"}}],"type":"one-column-empty"},{"content":{"style":{"background-image":"none","background-repeat":"no-repeat","color":"#333","width":"650px","background-position":"top left","background-color":"#F2ECE0"},"computedStyle":{"rowColStackOnMobile":true}},"container":{"style":{"background-image":"none","background-position":"top left","background-repeat":"no-repeat","background-color":"#E2DFD7"}},"locked":false,"columns":[{"grid-columns":6,"modules":[{"descriptor":{"image":{"src":"https://d15k2d11r6t6rl.cloudfront.net/public/users/Integrators/19b7eae6-38f6-4531-a9f9-0c76e74fab9f/leadsengage_int379/picev1.png","alt":"Image","href":""},"style":{"width":"100%","padding-top":"0px","padding-right":"0px","padding-left":"0px","padding-bottom":"0px"},"computedStyle":{"width":300,"class":"left  autowidth ","hideContentOnMobile":false}},"type":"mailup-bee-newsletter-modules-image","locked":false}],"style":{"padding-bottom":"5px","border-left":"0px solid transparent","border-bottom":"0px solid transparent","border-top":"0px solid transparent","padding-right":"0px","border-right":"0px solid transparent","padding-top":"5px","background-color":"transparent","padding-left":"0px"}},{"grid-columns":6,"modules":[{"descriptor":{"text":{"style":{"color":"#555555","font-family":"'Montserrat', 'Trebuchet MS', 'Lucida Grande', 'Lucida Sans Unicode', 'Lucida Sans', Tahoma, sans-serif","line-height":"120%"},"html":"<div class=\"txtTinyMce-wrapper\" style=\"font-size: 12px; line-height: 14px; font-family: Montserrat, 'Trebuchet MS', 'Lucida Grande', 'Lucida Sans Unicode', 'Lucida Sans', Tahoma, sans-serif;\" data-mce-style=\"font-size: 12px; line-height: 14px; font-family: Montserrat, 'Trebuchet MS', 'Lucida Grande', 'Lucida Sans Unicode', 'Lucida Sans', Tahoma, sans-serif;\">\n<p style=\"font-size: 14px; line-height: 16px;\" data-mce-style=\"font-size: 14px; line-height: 16px;\"><strong><span style=\"font-size: 16px; line-height: 19px;\" data-mce-style=\"font-size: 16px; line-height: 19px;\">TITLE OF THIS ARTICLE</span></strong></p>\n</div>","computedStyle":{"linkColor":"#0068A5"}},"style":{"padding-top":"20px","padding-right":"10px","padding-left":"15px","padding-bottom":"10px"},"computedStyle":{"hideContentOnMobile":false}},"type":"mailup-bee-newsletter-modules-text","locked":false},{"descriptor":{"text":{"style":{"color":"#555555","font-family":"'Roboto', Tahoma, Verdana, Segoe, sans-serif","line-height":"120%"},"html":"<div class=\"txtTinyMce-wrapper\" style=\"font-size: 12px; line-height: 14px; font-family: Roboto, Tahoma, Verdana, Segoe, sans-serif;\" data-mce-style=\"font-size: 12px; line-height: 14px; font-family: Roboto, Tahoma, Verdana, Segoe, sans-serif;\">\n<p style=\"font-size: 14px; line-height: 16px;\" data-mce-style=\"font-size: 14px; line-height: 16px;\">I'm a new Text block ready for your content.I'm a new Text block ready for your content.I'm a new Text.</p>\n</div>","computedStyle":{"linkColor":"#0068A5"}},"style":{"padding-top":"10px","padding-right":"30px","padding-left":"15px","padding-bottom":"10px"},"computedStyle":{"hideContentOnMobile":false}},"type":"mailup-bee-newsletter-modules-text","locked":false},{"descriptor":{"button":{"style":{"border-radius":"23px","color":"#ffffff","border-left":"0px solid transparent","border-bottom":"0px solid transparent","width":"auto","border-top":"0px solid transparent","padding-right":"20px","padding-bottom":"5px","max-width":"100%","border-right":"0px solid transparent","padding-top":"5px","font-family":"'Roboto', Tahoma, Verdana, Segoe, sans-serif","line-height":"200%","background-color":"#4C414A","padding-left":"20px"},"href":"","label":"<div class=\"txtTinyMce-wrapper\" style=\"font-size: 12px; line-height: 24px; font-family: Roboto, Tahoma, Verdana, Segoe, sans-serif;\">\n<p style=\"font-family: inherit; font-size: 16px; line-height: 32px;\"><span style=\"font-size: 14px; line-height: 28px;\">READ MORE</span></p>\n</div>"},"style":{"padding-left":"15px","padding-top":"5px","padding-right":"20px","padding-bottom":"5px","text-align":"left"},"computedStyle":{"width":76,"hideContentOnMobile":false,"height":42}},"type":"mailup-bee-newsletter-modules-button","locked":false}],"style":{"padding-bottom":"5px","border-left":"0px solid transparent","border-bottom":"0px solid transparent","border-top":"0px solid transparent","padding-right":"0px","border-right":"0px solid transparent","padding-top":"5px","background-color":"transparent","padding-left":"0px"}}],"type":"two-columns-empty"},{"content":{"style":{"background-image":"none","background-repeat":"no-repeat","color":"#000000","width":"650px","background-position":"top left","background-color":"#F2ECE0"},"computedStyle":{"rowColStackOnMobile":true}},"container":{"style":{"background-image":"none","background-position":"top left","background-repeat":"no-repeat","background-color":"#E2DFD7"}},"locked":false,"columns":[{"grid-columns":12,"modules":[{"descriptor":{"image":{"src":"https://d15k2d11r6t6rl.cloudfront.net/public/users/Integrators/19b7eae6-38f6-4531-a9f9-0c76e74fab9f/leadsengage_int379/line.png","alt":"Image","href":""},"style":{"width":"100%"},"computedStyle":{"width":650,"class":"center  autowidth  fullwidth","hideContentOnMobile":false}},"type":"mailup-bee-newsletter-modules-image","locked":false}],"style":{"padding-bottom":"0px","border-left":"0px solid transparent","border-bottom":"0px solid transparent","border-top":"0px solid transparent","padding-right":"0px","border-right":"0px solid transparent","padding-top":"0px","background-color":"transparent","padding-left":"0px"}}],"type":"one-column-empty"},{"content":{"style":{"background-image":"none","background-repeat":"no-repeat","color":"#333","width":"650px","background-position":"top left","background-color":"#FFFFFF"},"computedStyle":{"rowColStackOnMobile":true}},"container":{"style":{"background-image":"none","background-position":"top left","background-repeat":"no-repeat","background-color":"#E2DFD7"}},"locked":false,"columns":[{"grid-columns":6,"modules":[{"descriptor":{"text":{"style":{"color":"#555555","font-family":"'Montserrat', 'Trebuchet MS', 'Lucida Grande', 'Lucida Sans Unicode', 'Lucida Sans', Tahoma, sans-serif","line-height":"120%"},"html":"<div class=\"txtTinyMce-wrapper\" style=\"font-size: 12px; line-height: 14px; font-family: Montserrat, 'Trebuchet MS', 'Lucida Grande', 'Lucida Sans Unicode', 'Lucida Sans', Tahoma, sans-serif;\" data-mce-style=\"font-size: 12px; line-height: 14px; font-family: Montserrat, 'Trebuchet MS', 'Lucida Grande', 'Lucida Sans Unicode', 'Lucida Sans', Tahoma, sans-serif;\">\n<p style=\"font-size: 14px; line-height: 16px;\" data-mce-style=\"font-size: 14px; line-height: 16px;\"><strong><span style=\"font-size: 16px; line-height: 19px;\" data-mce-style=\"font-size: 16px; line-height: 19px;\">TITLE OF THIS ARTICLE</span></strong></p>\n</div>","computedStyle":{"linkColor":"#0068A5"}},"style":{"padding-top":"20px","padding-right":"10px","padding-left":"15px","padding-bottom":"10px"},"computedStyle":{"hideContentOnMobile":false}},"type":"mailup-bee-newsletter-modules-text","locked":false},{"descriptor":{"text":{"style":{"color":"#555555","font-family":"'Roboto', Tahoma, Verdana, Segoe, sans-serif","line-height":"120%"},"html":"<div class=\"txtTinyMce-wrapper\" style=\"font-size: 12px; line-height: 14px; font-family: Roboto, Tahoma, Verdana, Segoe, sans-serif;\" data-mce-style=\"font-size: 12px; line-height: 14px; font-family: Roboto, Tahoma, Verdana, Segoe, sans-serif;\">\n<p style=\"font-size: 14px; line-height: 16px;\" data-mce-style=\"font-size: 14px; line-height: 16px;\">I'm a new Text block ready for your content.I'm a new Text block ready for your content.I'm a new Text.</p>\n</div>","computedStyle":{"linkColor":"#0068A5"}},"style":{"padding-top":"10px","padding-right":"30px","padding-left":"15px","padding-bottom":"10px"},"computedStyle":{"hideContentOnMobile":false}},"type":"mailup-bee-newsletter-modules-text","locked":false},{"descriptor":{"button":{"style":{"border-radius":"23px","color":"#ffffff","border-left":"0px solid transparent","border-bottom":"0px solid transparent","width":"auto","border-top":"0px solid transparent","padding-right":"20px","padding-bottom":"5px","max-width":"100%","border-right":"0px solid transparent","padding-top":"5px","font-family":"'Roboto', Tahoma, Verdana, Segoe, sans-serif","line-height":"200%","background-color":"#4C414A","padding-left":"20px"},"href":"","label":"<div class=\"txtTinyMce-wrapper\" style=\"font-size: 12px; line-height: 24px; font-family: Roboto, Tahoma, Verdana, Segoe, sans-serif;\">\n<p style=\"font-family: inherit; font-size: 16px; line-height: 32px;\"><span style=\"font-size: 14px; line-height: 28px;\">READ MORE</span></p>\n</div>"},"style":{"padding-left":"15px","padding-top":"5px","padding-right":"20px","padding-bottom":"5px","text-align":"left"},"computedStyle":{"width":76,"hideContentOnMobile":false,"height":42}},"type":"mailup-bee-newsletter-modules-button","locked":false}],"style":{"padding-bottom":"5px","border-left":"0px solid transparent","border-bottom":"0px solid transparent","border-top":"0px solid transparent","padding-right":"0px","border-right":"0px solid transparent","padding-top":"5px","background-color":"transparent","padding-left":"0px"}},{"grid-columns":6,"modules":[{"descriptor":{"image":{"src":"https://d15k2d11r6t6rl.cloudfront.net/public/users/Integrators/19b7eae6-38f6-4531-a9f9-0c76e74fab9f/leadsengage_int379/picc.png","alt":"Image","href":""},"style":{"width":"100%","padding-top":"0px","padding-right":"0px","padding-left":"0px","padding-bottom":"0px"},"computedStyle":{"width":300,"class":"right  autowidth ","hideContentOnMobile":false}},"type":"mailup-bee-newsletter-modules-image","locked":false}],"style":{"padding-bottom":"5px","border-left":"0px solid transparent","border-bottom":"0px solid transparent","border-top":"0px solid transparent","padding-right":"0px","border-right":"0px solid transparent","padding-top":"5px","background-color":"transparent","padding-left":"0px"}}],"type":"two-columns-empty"},{"content":{"style":{"background-image":"none","background-repeat":"no-repeat","color":"#000000","width":"650px","background-position":"top left","background-color":"transparent"},"computedStyle":{"rowColStackOnMobile":true}},"container":{"style":{"background-image":"none","background-position":"top left","background-repeat":"no-repeat","background-color":"#E2DFD7"}},"locked":false,"columns":[{"grid-columns":12,"modules":[{"descriptor":{"image":{"src":"https://d15k2d11r6t6rl.cloudfront.net/public/users/Integrators/19b7eae6-38f6-4531-a9f9-0c76e74fab9f/leadsengage_int379/line2.png","alt":"Image","href":""},"style":{"width":"100%"},"computedStyle":{"width":650,"class":"center  autowidth  fullwidth","hideContentOnMobile":false}},"type":"mailup-bee-newsletter-modules-image","locked":false}],"style":{"padding-bottom":"0px","border-left":"0px solid transparent","border-bottom":"0px solid transparent","border-top":"0px solid transparent","padding-right":"0px","border-right":"0px solid transparent","padding-top":"0px","background-color":"transparent","padding-left":"0px"}}],"type":"one-column-empty"},{"content":{"style":{"background-image":"none","background-repeat":"no-repeat","color":"#000000","width":"650px","background-position":"top left","background-color":"#F2ECE0"},"computedStyle":{"rowColStackOnMobile":true}},"locked":false,"container":{"style":{"background-image":"none","background-position":"top left","background-repeat":"no-repeat","background-color":"#E2DFD7"}},"columns":[{"grid-columns":12,"modules":[{"descriptor":{"text":{"style":{"color":"#283C4B","font-family":"'Montserrat', 'Trebuchet MS', 'Lucida Grande', 'Lucida Sans Unicode', 'Lucida Sans', Tahoma, sans-serif","line-height":"120%"},"html":"<div class=\"txtTinyMce-wrapper\" style=\"font-size: 12px; line-height: 14px; font-family: Montserrat, 'Trebuchet MS', 'Lucida Grande', 'Lucida Sans Unicode', 'Lucida Sans', Tahoma, sans-serif;\" data-mce-style=\"font-size: 12px; line-height: 14px; font-family: Montserrat, 'Trebuchet MS', 'Lucida Grande', 'Lucida Sans Unicode', 'Lucida Sans', Tahoma, sans-serif;\">\n<p style=\"font-size: 14px; line-height: 16px; text-align: center;\" data-mce-style=\"font-size: 14px; line-height: 16px; text-align: center;\"><strong><span style=\"font-size: 20px; line-height: 24px;\" data-mce-style=\"font-size: 20px; line-height: 24px;\">TITLE OF THIS ARTICLE</span></strong></p>\n</div>","computedStyle":{"linkColor":"#0068A5"}},"style":{"padding-top":"10px","padding-right":"10px","padding-bottom":"10px","padding-left":"10px"},"computedStyle":{"hideContentOnMobile":false}},"type":"mailup-bee-newsletter-modules-text","locked":false},{"descriptor":{"image":{"src":"https://d15k2d11r6t6rl.cloudfront.net/public/users/Integrators/19b7eae6-38f6-4531-a9f9-0c76e74fab9f/leadsengage_int379/big3.png","alt":"Image","href":""},"style":{"width":"100%","padding-top":"10px","padding-right":"30px","padding-left":"30px","padding-bottom":"30px"},"computedStyle":{"width":590,"class":"center  autowidth  fullwidth","hideContentOnMobile":false}},"type":"mailup-bee-newsletter-modules-image","locked":false},{"descriptor":{"text":{"style":{"color":"#555555","font-family":"'Roboto', Tahoma, Verdana, Segoe, sans-serif","line-height":"150%"},"html":"<div class=\"txtTinyMce-wrapper\" style=\"font-size: 12px; line-height: 18px; font-family: Roboto, Tahoma, Verdana, Segoe, sans-serif;\" data-mce-style=\"font-size: 12px; line-height: 18px; font-family: Roboto, Tahoma, Verdana, Segoe, sans-serif;\">\n<p style=\"font-size: 14px; line-height: 21px; text-align: center;\" data-mce-style=\"font-size: 14px; line-height: 21px; text-align: center;\">I'm a new Text block ready for your content.I'm a new Text block ready for your content.I'm a new Text block ready for your content.I'm a new Text block ready for your content.I'm a new Text block ready for your content.</p>\n</div>","computedStyle":{"linkColor":"#0068A5"}},"style":{"padding-top":"0px","padding-right":"30px","padding-bottom":"5px","padding-left":"30px"},"computedStyle":{"hideContentOnMobile":false}},"type":"mailup-bee-newsletter-modules-text","locked":false},{"descriptor":{"button":{"style":{"border-radius":"23px","color":"#ffffff","padding-bottom":"5px","border-bottom":"0px solid transparent","width":"auto","border-top":"0px solid transparent","padding-right":"20px","border-left":"0px solid transparent","max-width":"100%","border-right":"0px solid transparent","padding-top":"5px","font-family":"'Roboto', Tahoma, Verdana, Segoe, sans-serif","line-height":"200%","background-color":"#4C414A","padding-left":"20px"},"href":"","label":"<div class=\"txtTinyMce-wrapper\" style=\"font-size: 12px; line-height: 24px; font-family: Roboto, Tahoma, Verdana, Segoe, sans-serif;\">\n<p style=\"font-family: inherit; font-size: 16px; line-height: 32px;\"><strong><span style=\"font-size: 14px; line-height: 28px;\">READ MORE</span></strong></p>\n</div>"},"style":{"text-align":"center","padding-top":"10px","padding-right":"10px","padding-bottom":"10px","padding-left":"10px"},"computedStyle":{"width":100,"hideContentOnMobile":false,"height":42}},"type":"mailup-bee-newsletter-modules-button","locked":false}],"style":{"padding-bottom":"5px","border-left":"0px solid transparent","border-bottom":"0px solid transparent","border-top":"0px solid transparent","padding-right":"0px","border-right":"0px solid transparent","padding-top":"5px","background-color":"transparent","padding-left":"0px"}}],"type":"one-column-empty"},{"content":{"style":{"background-image":"none","background-repeat":"no-repeat","color":"#000000","width":"650px","background-position":"top left","background-color":"#F2ECE0"},"computedStyle":{"rowColStackOnMobile":true}},"container":{"style":{"background-image":"none","background-position":"top left","background-repeat":"no-repeat","background-color":"#E2DFD7"}},"locked":false,"columns":[{"grid-columns":12,"modules":[{"descriptor":{"image":{"src":"https://d15k2d11r6t6rl.cloudfront.net/public/users/Integrators/19b7eae6-38f6-4531-a9f9-0c76e74fab9f/leadsengage_int379/line3.png","alt":"Image","href":""},"style":{"width":"100%","padding-top":"0px","padding-right":"0px","padding-left":"0px","padding-bottom":"0px"},"computedStyle":{"width":650,"class":"center  autowidth  fullwidth","hideContentOnMobile":false}},"type":"mailup-bee-newsletter-modules-image","locked":false}],"style":{"padding-bottom":"0px","border-left":"0px solid transparent","border-bottom":"0px solid transparent","border-top":"0px solid transparent","padding-right":"0px","border-right":"0px solid transparent","padding-top":"0px","background-color":"transparent","padding-left":"0px"}}],"type":"one-column-empty"},{"content":{"style":{"background-image":"none","background-repeat":"no-repeat","color":"#000000","width":"650px","background-position":"top left","background-color":"#FFFFFF"},"computedStyle":{"rowColStackOnMobile":true}},"container":{"style":{"background-image":"none","background-position":"top left","background-repeat":"no-repeat","background-color":"#E2DFD7"}},"locked":false,"columns":[{"grid-columns":4,"modules":[{"descriptor":{"image":{"src":"https://d15k2d11r6t6rl.cloudfront.net/public/users/Integrators/19b7eae6-38f6-4531-a9f9-0c76e74fab9f/leadsengage_int379/ic2.png","alt":"Image","href":""},"style":{"width":"100%"},"computedStyle":{"width":118,"class":"center  autowidth ","hideContentOnMobile":false}},"type":"mailup-bee-newsletter-modules-image","locked":false},{"descriptor":{"text":{"style":{"color":"#555555","font-family":"'Montserrat', 'Trebuchet MS', 'Lucida Grande', 'Lucida Sans Unicode', 'Lucida Sans', Tahoma, sans-serif","line-height":"120%"},"html":"<div class=\"txtTinyMce-wrapper\" style=\"font-size: 12px; line-height: 14px; font-family: Montserrat, 'Trebuchet MS', 'Lucida Grande', 'Lucida Sans Unicode', 'Lucida Sans', Tahoma, sans-serif;\" data-mce-style=\"font-size: 12px; line-height: 14px; font-family: Montserrat, 'Trebuchet MS', 'Lucida Grande', 'Lucida Sans Unicode', 'Lucida Sans', Tahoma, sans-serif;\">\n<p style=\"font-size: 14px; line-height: 16px; text-align: center;\" data-mce-style=\"font-size: 14px; line-height: 16px; text-align: center;\"><strong>LOREM IPSUM</strong></p>\n</div>","computedStyle":{"linkColor":"#0068A5"}},"style":{"padding-top":"10px","padding-right":"10px","padding-left":"10px","padding-bottom":"10px"},"computedStyle":{"hideContentOnMobile":false}},"type":"mailup-bee-newsletter-modules-text","locked":false},{"descriptor":{"text":{"style":{"color":"#555555","font-family":"'Roboto', Tahoma, Verdana, Segoe, sans-serif","line-height":"120%"},"html":"<div class=\"txtTinyMce-wrapper\" style=\"font-size: 12px; line-height: 14px; font-family: Roboto, Tahoma, Verdana, Segoe, sans-serif;\" data-mce-style=\"font-size: 12px; line-height: 14px; font-family: Roboto, Tahoma, Verdana, Segoe, sans-serif;\">\n<p style=\"font-size: 14px; line-height: 16px; text-align: center;\" data-mce-style=\"font-size: 14px; line-height: 16px; text-align: center;\">I'm a new Text block ready for your content.I'm a new Text block ready for your.</p>\n</div>","computedStyle":{"linkColor":"#0068A5"}},"style":{"padding-top":"10px","padding-right":"10px","padding-left":"10px","padding-bottom":"10px"},"computedStyle":{"hideContentOnMobile":false}},"type":"mailup-bee-newsletter-modules-text","locked":false}],"style":{"padding-bottom":"5px","border-left":"0px solid transparent","border-bottom":"0px solid transparent","border-top":"0px solid transparent","padding-right":"0px","border-right":"0px solid transparent","padding-top":"5px","background-color":"transparent","padding-left":"0px"}},{"grid-columns":4,"modules":[{"descriptor":{"image":{"src":"https://d15k2d11r6t6rl.cloudfront.net/public/users/Integrators/19b7eae6-38f6-4531-a9f9-0c76e74fab9f/leadsengage_int379/ic1.png","alt":"Image","href":""},"style":{"width":"100%"},"computedStyle":{"width":118,"class":"center  autowidth ","hideContentOnMobile":false}},"type":"mailup-bee-newsletter-modules-image","locked":false},{"descriptor":{"text":{"style":{"color":"#555555","font-family":"'Montserrat', 'Trebuchet MS', 'Lucida Grande', 'Lucida Sans Unicode', 'Lucida Sans', Tahoma, sans-serif","line-height":"120%"},"html":"<div class=\"txtTinyMce-wrapper\" style=\"font-size: 12px; line-height: 14px; font-family: Montserrat, 'Trebuchet MS', 'Lucida Grande', 'Lucida Sans Unicode', 'Lucida Sans', Tahoma, sans-serif;\" data-mce-style=\"font-size: 12px; line-height: 14px; font-family: Montserrat, 'Trebuchet MS', 'Lucida Grande', 'Lucida Sans Unicode', 'Lucida Sans', Tahoma, sans-serif;\">\n<p style=\"font-size: 14px; line-height: 16px; text-align: center;\" data-mce-style=\"font-size: 14px; line-height: 16px; text-align: center;\"><strong>DOLOR SIT AMET</strong></p>\n</div>","computedStyle":{"linkColor":"#0068A5"}},"style":{"padding-top":"10px","padding-right":"10px","padding-left":"10px","padding-bottom":"10px"},"computedStyle":{"hideContentOnMobile":false}},"type":"mailup-bee-newsletter-modules-text","locked":false},{"descriptor":{"text":{"style":{"color":"#555555","font-family":"'Roboto', Tahoma, Verdana, Segoe, sans-serif","line-height":"120%"},"html":"<div class=\"txtTinyMce-wrapper\" style=\"font-size: 12px; line-height: 14px; font-family: Roboto, Tahoma, Verdana, Segoe, sans-serif;\" data-mce-style=\"font-size: 12px; line-height: 14px; font-family: Roboto, Tahoma, Verdana, Segoe, sans-serif;\">\n<p style=\"font-size: 14px; line-height: 16px; text-align: center;\" data-mce-style=\"font-size: 14px; line-height: 16px; text-align: center;\">I'm a new Text block ready for your content.I'm a new Text block ready for your.</p>\n</div>","computedStyle":{"linkColor":"#0068A5"}},"style":{"padding-top":"10px","padding-right":"10px","padding-left":"10px","padding-bottom":"10px"},"computedStyle":{"hideContentOnMobile":false}},"type":"mailup-bee-newsletter-modules-text","locked":false}],"style":{"padding-bottom":"5px","border-left":"0px solid transparent","border-bottom":"0px solid transparent","border-top":"0px solid transparent","padding-right":"0px","border-right":"0px solid transparent","padding-top":"5px","background-color":"transparent","padding-left":"0px"}},{"grid-columns":4,"modules":[{"descriptor":{"image":{"src":"https://d15k2d11r6t6rl.cloudfront.net/public/users/Integrators/19b7eae6-38f6-4531-a9f9-0c76e74fab9f/leadsengage_int379/ic3.png","alt":"Image","href":""},"style":{"width":"100%"},"computedStyle":{"width":118,"class":"center  autowidth ","hideContentOnMobile":false}},"type":"mailup-bee-newsletter-modules-image","locked":false},{"descriptor":{"text":{"style":{"color":"#555555","font-family":"'Montserrat', 'Trebuchet MS', 'Lucida Grande', 'Lucida Sans Unicode', 'Lucida Sans', Tahoma, sans-serif","line-height":"120%"},"html":"<div class=\"txtTinyMce-wrapper\" style=\"font-size: 12px; line-height: 14px; font-family: Montserrat, 'Trebuchet MS', 'Lucida Grande', 'Lucida Sans Unicode', 'Lucida Sans', Tahoma, sans-serif;\" data-mce-style=\"font-size: 12px; line-height: 14px; font-family: Montserrat, 'Trebuchet MS', 'Lucida Grande', 'Lucida Sans Unicode', 'Lucida Sans', Tahoma, sans-serif;\">\n<p style=\"font-size: 14px; line-height: 16px; text-align: center;\" data-mce-style=\"font-size: 14px; line-height: 16px; text-align: center;\"><strong>CONSECURETUR</strong></p>\n</div>","computedStyle":{"linkColor":"#0068A5"}},"style":{"padding-top":"10px","padding-right":"10px","padding-left":"10px","padding-bottom":"10px"},"computedStyle":{"hideContentOnMobile":false}},"type":"mailup-bee-newsletter-modules-text","locked":false},{"descriptor":{"text":{"style":{"color":"#555555","font-family":"'Roboto', Tahoma, Verdana, Segoe, sans-serif","line-height":"120%"},"html":"<div class=\"txtTinyMce-wrapper\" style=\"font-size: 12px; line-height: 14px; font-family: Roboto, Tahoma, Verdana, Segoe, sans-serif;\" data-mce-style=\"font-size: 12px; line-height: 14px; font-family: Roboto, Tahoma, Verdana, Segoe, sans-serif;\">\n<p style=\"font-size: 14px; line-height: 16px; text-align: center;\" data-mce-style=\"font-size: 14px; line-height: 16px; text-align: center;\">I'm a new Text block ready for your content.I'm a new Text block ready for your.</p>\n</div>","computedStyle":{"linkColor":"#0068A5"}},"style":{"padding-top":"10px","padding-right":"10px","padding-left":"10px","padding-bottom":"10px"},"computedStyle":{"hideContentOnMobile":false}},"type":"mailup-bee-newsletter-modules-text","locked":false}],"style":{"padding-bottom":"5px","border-left":"0px solid transparent","border-bottom":"0px solid transparent","border-top":"0px solid transparent","padding-right":"0px","border-right":"0px solid transparent","padding-top":"5px","background-color":"transparent","padding-left":"0px"}}],"type":"three-columns-empty"},{"content":{"style":{"background-image":"none","background-repeat":"no-repeat","color":"#000000","width":"650px","background-position":"top left","background-color":"#F2ECE0"},"computedStyle":{"rowColStackOnMobile":true}},"container":{"style":{"background-image":"none","background-position":"top left","background-repeat":"no-repeat","background-color":"#E2DFD7"}},"locked":false,"columns":[{"grid-columns":12,"modules":[{"descriptor":{"image":{"src":"https://d15k2d11r6t6rl.cloudfront.net/public/users/Integrators/19b7eae6-38f6-4531-a9f9-0c76e74fab9f/leadsengage_int379/line2.png","alt":"Image","href":""},"style":{"width":"100%"},"computedStyle":{"width":650,"class":"center  autowidth  fullwidth","hideContentOnMobile":false}},"type":"mailup-bee-newsletter-modules-image","locked":false}],"style":{"padding-bottom":"5px","border-left":"0px solid transparent","border-bottom":"0px solid transparent","border-top":"0px solid transparent","padding-right":"0px","border-right":"0px solid transparent","padding-top":"5px","background-color":"transparent","padding-left":"0px"}}],"type":"one-column-empty"},{"content":{"style":{"background-image":"none","background-repeat":"no-repeat","color":"#333","width":"650px","background-position":"top left","background-color":"#F2ECE0"},"computedStyle":{"rowColStackOnMobile":true}},"container":{"style":{"background-image":"none","background-position":"top left","background-repeat":"no-repeat","background-color":"#E2DFD7"}},"locked":false,"columns":[{"grid-columns":6,"modules":[{"descriptor":{"image":{"src":"https://d15k2d11r6t6rl.cloudfront.net/public/users/Integrators/19b7eae6-38f6-4531-a9f9-0c76e74fab9f/leadsengage_int379/imgev2.png","alt":"Image","href":""},"style":{"width":"100%","padding-top":"0px","padding-right":"0px","padding-left":"0px","padding-bottom":"0px"},"computedStyle":{"width":300,"class":"left  autowidth ","hideContentOnMobile":false}},"type":"mailup-bee-newsletter-modules-image","locked":false}],"style":{"padding-bottom":"5px","border-left":"0px solid transparent","border-bottom":"0px solid transparent","border-top":"0px solid transparent","padding-right":"0px","border-right":"0px solid transparent","padding-top":"5px","background-color":"transparent","padding-left":"0px"}},{"grid-columns":6,"modules":[{"descriptor":{"text":{"style":{"color":"#555555","font-family":"'Montserrat', 'Trebuchet MS', 'Lucida Grande', 'Lucida Sans Unicode', 'Lucida Sans', Tahoma, sans-serif","line-height":"120%"},"html":"<div class=\"txtTinyMce-wrapper\" style=\"font-size: 12px; line-height: 14px; font-family: Montserrat, 'Trebuchet MS', 'Lucida Grande', 'Lucida Sans Unicode', 'Lucida Sans', Tahoma, sans-serif;\" data-mce-style=\"font-size: 12px; line-height: 14px; font-family: Montserrat, 'Trebuchet MS', 'Lucida Grande', 'Lucida Sans Unicode', 'Lucida Sans', Tahoma, sans-serif;\">\n<p style=\"font-size: 14px; line-height: 16px;\" data-mce-style=\"font-size: 14px; line-height: 16px;\"><strong><span style=\"font-size: 16px; line-height: 19px;\" data-mce-style=\"font-size: 16px; line-height: 19px;\">TITLE OF THIS ARTICLE</span></strong></p>\n</div>","computedStyle":{"linkColor":"#0068A5"}},"style":{"padding-top":"20px","padding-right":"10px","padding-left":"15px","padding-bottom":"10px"},"computedStyle":{"hideContentOnMobile":false}},"type":"mailup-bee-newsletter-modules-text","locked":false},{"descriptor":{"text":{"style":{"color":"#555555","font-family":"'Roboto', Tahoma, Verdana, Segoe, sans-serif","line-height":"120%"},"html":"<div class=\"txtTinyMce-wrapper\" style=\"font-size: 12px; line-height: 14px; font-family: Roboto, Tahoma, Verdana, Segoe, sans-serif;\" data-mce-style=\"font-size: 12px; line-height: 14px; font-family: Roboto, Tahoma, Verdana, Segoe, sans-serif;\">\n<p style=\"font-size: 14px; line-height: 16px;\" data-mce-style=\"font-size: 14px; line-height: 16px;\">I'm a new Text block ready for your content.I'm a new Text block ready for your content.I'm a new Text.</p>\n</div>","computedStyle":{"linkColor":"#0068A5"}},"style":{"padding-top":"10px","padding-right":"30px","padding-left":"15px","padding-bottom":"10px"},"computedStyle":{"hideContentOnMobile":false}},"type":"mailup-bee-newsletter-modules-text","locked":false},{"descriptor":{"button":{"style":{"border-radius":"23px","color":"#ffffff","border-left":"0px solid transparent","border-bottom":"0px solid transparent","width":"auto","border-top":"0px solid transparent","padding-right":"20px","padding-bottom":"5px","max-width":"100%","border-right":"0px solid transparent","padding-top":"5px","font-family":"'Roboto', Tahoma, Verdana, Segoe, sans-serif","line-height":"200%","background-color":"#4C414A","padding-left":"20px"},"href":"","label":"<div class=\"txtTinyMce-wrapper\" style=\"font-size: 12px; line-height: 24px; font-family: Roboto, Tahoma, Verdana, Segoe, sans-serif;\">\n<p style=\"font-family: inherit; font-size: 16px; line-height: 32px;\"><span style=\"font-size: 14px; line-height: 28px;\">READ MORE</span></p>\n</div>"},"style":{"padding-left":"15px","padding-top":"5px","padding-right":"20px","padding-bottom":"5px","text-align":"left"},"computedStyle":{"width":76,"hideContentOnMobile":false,"height":42}},"type":"mailup-bee-newsletter-modules-button","locked":false}],"style":{"padding-bottom":"5px","border-left":"0px solid transparent","border-bottom":"0px solid transparent","border-top":"0px solid transparent","padding-right":"0px","border-right":"0px solid transparent","padding-top":"5px","background-color":"transparent","padding-left":"0px"}}],"type":"two-columns-empty"},{"content":{"style":{"background-image":"none","background-repeat":"no-repeat","color":"#000000","width":"650px","background-position":"top left","background-color":"#F2ECE0"},"computedStyle":{"rowColStackOnMobile":true}},"container":{"style":{"background-image":"none","background-position":"top left","background-repeat":"no-repeat","background-color":"#E2DFD7"}},"locked":false,"columns":[{"grid-columns":12,"modules":[{"descriptor":{"text":{"style":{"color":"#555555","font-family":"inherit","line-height":"120%"},"html":"<div class=\"txtTinyMce-wrapper\" data-mce-style=\"font-size: 12px; line-height: 14px;\" style=\"font-size: 12px; line-height: 14px;\"><p data-mce-style=\"font-size: 12px; line-height: 14px;\" style=\"font-size: 12px; line-height: 14px;\"><br data-mce-bogus=\"1\"></p></div>","computedStyle":{"linkColor":"#0068A5"}},"style":{"padding-top":"10px","padding-right":"10px","padding-left":"10px","padding-bottom":"10px"},"computedStyle":{"hideContentOnMobile":false}},"type":"mailup-bee-newsletter-modules-text","locked":false}],"style":{"padding-bottom":"5px","border-left":"0px solid transparent","border-bottom":"0px solid transparent","border-top":"0px solid transparent","padding-right":"0px","border-right":"0px solid transparent","padding-top":"5px","background-color":"transparent","padding-left":"0px"}}],"type":"one-column-empty"},{"content":{"style":{"background-image":"none","background-repeat":"no-repeat","color":"#000000","width":"650px","background-position":"top left","background-color":"#4C414A"},"computedStyle":{"rowColStackOnMobile":true}},"locked":false,"container":{"style":{"background-image":"none","background-position":"top left","background-repeat":"no-repeat","background-color":"#E2DFD7"}},"columns":[{"grid-columns":12,"modules":[{"descriptor":{"style":{"text-align":"center","padding-top":"10px","padding-right":"10px","padding-bottom":"10px","padding-left":"10px"},"computedStyle":{"padding":"0 5px 5px 0","width":151,"hideContentOnMobile":false,"iconsDefaultWidth":32,"height":57},"iconsList":{"icons":[{"text":"","image":{"src":"https://app-rsrc.getbee.io/public/resources/social-networks-icon-sets/circle-color/facebook@2x.png","prefix":"https://www.facebook.com/","href":"https://www.facebook.com/","alt":"Facebook","title":"Facebook"},"type":"follow","name":"facebook"},{"text":"","image":{"src":"https://app-rsrc.getbee.io/public/resources/social-networks-icon-sets/circle-color/twitter@2x.png","prefix":"https://twitter.com/","href":"https://twitter.com/","alt":"Twitter","title":"Twitter"},"type":"follow","name":"twitter"},{"text":"","image":{"src":"https://app-rsrc.getbee.io/public/resources/social-networks-icon-sets/circle-color/googleplus@2x.png","prefix":"https://plus.google.com/","href":"https://plus.google.com/","alt":"Google+","title":"Google+"},"type":"follow","name":"google"}]}},"type":"mailup-bee-newsletter-modules-social","locked":false}],"style":{"padding-bottom":"10px","border-left":"0px solid transparent","border-bottom":"0px solid transparent","border-top":"0px solid transparent","padding-right":"0px","border-right":"0px solid transparent","padding-top":"10px","background-color":"transparent","padding-left":"0px"}}],"type":"one-column-empty"}],"description":"","template":{"version":"2.0.0","type":"basic","name":"template-base"},"title":""}}